setup.py
epasts/__init__.py
epasts/exceptions.py
epasts/mailer.py
epasts/message.py
epasts/response.py
epasts.egg-info/PKG-INFO
epasts.egg-info/SOURCES.txt
epasts.egg-info/dependency_links.txt
epasts.egg-info/top_level.txt