Metadata-Version: 1.0
Name: epasts
Version: 0.1b2
Summary: Simple email handling library.
Home-page: http://bitbucket.org/adrians/epasts
Author: Adrians Heidens
Author-email: adrians.heidens@gmail.com
License: BSD
Download-URL: http://bitbucket.org/adrians/epasts/downloads
Platform: UNKNOWN
